django_social_timeline-0.2.dist-info/metadata.json
django_social_timeline-0.2.dist-info/WHEEL
django_social_timeline-0.2.dist-info/top_level.txt
django_social_timeline-0.2.dist-info/RECORD
django_social_timeline-0.2.dist-info/DESCRIPTION.rst
django_social_timeline-0.2.dist-info/METADATA
social_demo/settings.py
social_demo/urls.py
social_demo/wsgi.py
social_demo/__init__.py
social_timeline/models.py
social_timeline/mixin.py
social_timeline/tests.py
social_timeline/api_views.py
social_timeline/serializers.py
social_timeline/__init__.py
social_timeline/admin.py
social_timeline/migrations/0002_auto_20150330_2120.py
social_timeline/migrations/0001_initial.py
social_timeline/migrations/__init__.py
