Metadata-Version: 2.0
Name: django-social-timeline
Version: 0.2
Summary: Social networking for django. Following system and timeline of events.
Home-page: https://github.com/thelabnyc/django-social-timeline
Author: David Burke
Author-email: david@thelabnyc.com
License: Apache License
Keywords: django,social networking
Platform: UNKNOWN
Classifier: Development Status :: 3 - Alpha
Classifier: Environment :: Web Environment
Classifier: Framework :: Django
Classifier: Programming Language :: Python
Classifier: Programming Language :: Python :: 3.4
Classifier: Intended Audience :: Developers
Classifier: License :: OSI Approved :: Apache Software License
